pyvdirs/dirs.py
pyvdirs-1.0.0.dist-info/LICENSE
pyvdirs-1.0.0.dist-info/METADATA
pyvdirs-1.0.0.dist-info/WHEEL
pyvdirs-1.0.0.dist-info/top_level.txt
pyvdirs-1.0.0.dist-info/RECORD
