Metadata-Version: 2.1
Name: pyvdirs
Version: 1.0.0
Summary: Python package to locally manage directories
Author-email: Valeria Pais <valeriarpais@gmail.com>
License: MIT License
Project-URL: Repository, https://github.com/0xInfty/PyVDirs.git
Project-URL: Homepage, https://github.com/0xInfty/PyVDirs
Project-URL: Issues, https://github.com/0xInfty/PyVDirs/issues
Keywords: directories,local
Classifier: Development Status :: 3 - Alpha
Classifier: License :: OSI Approved :: MIT License
Classifier: Programming Language :: Python :: 3
License-File: LICENSE
